setup.py
clash/__init__.py
clash/config.py
clash/functions.py
clash/loader.py
clash/module.py
clash/output.py
clash/state.py
clash.egg-info/PKG-INFO
clash.egg-info/SOURCES.txt
clash.egg-info/dependency_links.txt
clash.egg-info/not-zip-safe
clash.egg-info/requires.txt
clash.egg-info/top_level.txt