Metadata-Version: 1.0
Name: clash
Version: 0.14
Summary: Framework to wrap Cloudify local based blueprints as CLIs
Home-page: UNKNOWN
Author: GigaSpaces
Author-email: cosmo-admin@gigaspaces.com
License: Apache License, Version 2.0
Platform: UNKNOWN
